ocr_iiif_tools/__init__.py
ocr_iiif_tools/_modidx.py
ocr_iiif_tools/core.py
ocr_iiif_tools/pdf.py
ocr_iiif_tools-0.0.17.dist-info/LICENSE
ocr_iiif_tools-0.0.17.dist-info/METADATA
ocr_iiif_tools-0.0.17.dist-info/WHEEL
ocr_iiif_tools-0.0.17.dist-info/entry_points.txt
ocr_iiif_tools-0.0.17.dist-info/top_level.txt
ocr_iiif_tools-0.0.17.dist-info/RECORD
