Metadata-Version: 2.1
Name: ocr-iiif-tools
Version: 0.0.17
Summary: UNKNOWN
Home-page: https://github.com/nakamura196/ocr_iiif_tools
Author: Satoru
Author-email: you@example.com
License: Apache Software License 2.0
Keywords: nbdev jupyter notebook python
Platform: UNKNOWN
Classifier: Development Status :: 4 - Beta
Classifier: Intended Audience :: Developers
Classifier: Natural Language :: English
Classifier: Programming Language :: Python :: 3.7
Classifier: Programming Language :: Python :: 3.8
Classifier: Programming Language :: Python :: 3.9
Classifier: Programming Language :: Python :: 3.10
Classifier: License :: OSI Approved :: Apache Software License
Requires-Python: >=3.7
License-File: LICENSE
Requires-Dist: reportlab (==3.6.9)
Requires-Dist: requests
Requires-Dist: tqdm
Requires-Dist: beautifulsoup4
Provides-Extra: dev
